ghostos/__init__.py
ghostos/__main__.py
ghostos/abcd/__init__.py
ghostos/abcd/concepts.py
ghostos/abcd/ghosts.py
ghostos/abcd/memory.py
ghostos/abcd/realtime.py
ghostos/abcd/thoughts.py
ghostos/abcd/utils.py
ghostos/app/.example.env
ghostos/app/.gitignore
ghostos/app/.streamlit/config.toml
ghostos/app/assets/docs/ghostos/en/aifunc_introduction.md
ghostos/app/assets/docs/ghostos/zh/aifunc/introduction.md
ghostos/app/assets/docs/ghostos/zh/aifunc/request_info.md
ghostos/app/assets/docs/ghostos/zh/aifunc/usage_example.md
ghostos/app/configs/documents_registry.yml
ghostos/app/configs/ghostos_conf.yml
ghostos/app/configs/llms_conf.yml
ghostos/app/configs/openai_realtime_config.yml
ghostos/app/configs/realtime_conf.yml
ghostos/app/configs/registered_aifunc.yml
ghostos/app/configs/streamlit_app.yml
ghostos/app/memories/.gitkeep
ghostos/app/runtime/aifunc_frames/.gitignore
ghostos/app/runtime/audios/.gitignore
ghostos/app/runtime/cache/.gitignore
ghostos/app/runtime/events/.gitignore
ghostos/app/runtime/images/.gitignore
ghostos/app/runtime/logs/.gitignore
ghostos/app/runtime/processes/.gitignore
ghostos/app/runtime/prompts/.gitignore
ghostos/app/runtime/tasks/.gitignore
ghostos/app/runtime/threads/.gitignore
ghostos/app/runtime/variables/.gitignore
ghostos/app/source/.gitkeep
ghostos/bootstrap.py
ghostos/container.py
ghostos/contracts/README.md
ghostos/contracts/__init__.py
ghostos/contracts/assets.py
ghostos/contracts/cache.py
ghostos/contracts/configs.py
ghostos/contracts/documents.py
ghostos/contracts/logger.py
ghostos/contracts/modules.py
ghostos/contracts/pool.py
ghostos/contracts/shutdown.py
ghostos/contracts/storage.py
ghostos/contracts/translation.py
ghostos/contracts/variables.py
ghostos/contracts/workspace.py
ghostos/core/__init__.py
ghostos/core/aifunc/__init__.py
ghostos/core/aifunc/driver.py
ghostos/core/aifunc/executor.py
ghostos/core/aifunc/func.py
ghostos/core/aifunc/interfaces.py
ghostos/core/aifunc/repository.py
ghostos/core/llms/__init__.py
ghostos-0.3.0.dist-info/LICENSE
ghostos-0.3.0.dist-info/METADATA
ghostos-0.3.0.dist-info/WHEEL
ghostos-0.3.0.dist-info/entry_points.txt
ghostos-0.3.0.dist-info/RECORD
