Metadata-Version: 2.3
Name: ghostos
Version: 0.3.0
Summary: A framework offers an operating system simulator with a Python Code Interface for AI Agents
License: MIT
Author: zhuming
Author-email: thirdgerb@gmail.com
Requires-Python: >=3.10,<3.14
Classifier: License :: OSI Approved :: MIT License
Classifier: Programming Language :: Python :: 3
Classifier: Programming Language :: Python :: 3.10
Classifier: Programming Language :: Python :: 3.11
Classifier: Programming Language :: Python :: 3.12
Classifier: Programming Language :: Python :: 3.13
Provides-Extra: realtime
Provides-Extra: sphero
Requires-Dist: anthropic (>=0.31.2,<0.32.0)
Requires-Dist: arxiv (>=2.1.3,<3.0.0)
Requires-Dist: babel (>=2.16.0,<3.0.0)
Requires-Dist: bleak (>=0.22.3,<0.23.0) ; (python_version >= "3.10" and python_version < "3.14") and (extra == "sphero")
Requires-Dist: datasets (>=2.20.0,<3.0.0)
Requires-Dist: httpx-socks (>=0.9.1,<0.10.0)
Requires-Dist: litellm (>=1.43.18,<2.0.0)
Requires-Dist: llama-index-core (>=0.11.9,<0.12.0)
Requires-Dist: llama-index-llms-openai (>=0.2.7,<0.3.0)
Requires-Dist: openai (>=1.59.0,<2.0.0)
Requires-Dist: prompt-toolkit (>=3.0.47,<4.0.0)
Requires-Dist: pyaudio (>=0.2.14,<0.3.0) ; extra == "realtime"
Requires-Dist: pydantic (>=2.7.0,<3.0.0)
Requires-Dist: pydantic-settings (>=2.5.2,<3.0.0)
Requires-Dist: pysocks (>=1.7.1,<2.0.0)
Requires-Dist: python-dotenv (>=1.0.1,<2.0.0)
Requires-Dist: pyyaml (>=6.0.1,<7.0.0)
Requires-Dist: requests[socks] (>=2.32.3,<3.0.0)
Requires-Dist: rich (>=13.7.1,<14.0.0)
Requires-Dist: scipy (>=1.15.1,<2.0.0) ; extra == "realtime"
Requires-Dist: spherov2 (>=0.12.1,<0.13.0) ; extra == "sphero"
Requires-Dist: streamlit (>=1.39.0,<2.0.0)
Requires-Dist: streamlit-antd-components (>=0.3.2,<0.4.0)
Requires-Dist: streamlit-paste-button (>=0.1.2,<0.2.0)
Requires-Dist: streamlit-react-jsonschema (>=0.1.3,<0.2.0)
Requires-Dist: sympy (>=1.13.1,<2.0.0)
Requires-Dist: tree-sitter (==0.21.3)
Requires-Dist: tree-sitter-languages (>=1.10.2,<2.0.0)
Requires-Dist: websockets (>=13.1,<14.0)
Project-URL: Documentation, https://ghost-in-moss.github.io/GhostOS/#/en/
Project-URL: Homepage, https://github.com/ghost-in-moss/GhostOS
Project-URL: Issues, https://github.com/ghost-in-moss/GhostOS/issues
Project-URL: Repository, https://github.com/ghost-in-moss/GhostOS
